{"legislative_session": "2025", "identifier": "SB434", "title": "MATH & READING ACADEMIC SUPPORT", "from_organization": "~{\"classification\": \"upper\"}", "classification": ["bill"], "subject": ["EDUCATION, PUBLIC SCHOOLS"], "abstracts": [], "other_titles": [], "other_identifiers": [], "actions": [{"description": "Sent to Senate Education Committee & Senate Finance Committee", "date": "2025-02-18", "organization_id": "~{\"classification\": \"upper\"}", "classification": ["introduction", "referral-committee"], "related_entities": []}, {"description": "DO NOT PASS, replaced with committee substitute", "date": "2025-03-10", "organization_id": "~{\"classification\": \"upper\"}", "classification": ["committee-passage"], "related_entities": []}, {"description": "DO PASS, as amended, committee report adopted", "date": "2025-03-11", "organization_id": "~{\"classification\": \"upper\"}", "classification": ["committee-passage-favorable"], "related_entities": []}, {"description": "floor substitute adopted (1 amendment)", "date": "2025-03-13", "organization_id": "~{\"classification\": \"upper\"}", "classification": [], "related_entities": []}, {"description": "passed Senate", "date": "2025-03-13", "organization_id": "~{\"classification\": \"upper\"}", "classification": ["passage"], "related_entities": []}, {"description": "Sent to House Education Committee & House Government, Elections and Indian Affairs Committee", "date": "2025-03-13", "organization_id": "~{\"classification\": \"lower\"}", "classification": ["introduction", "referral-committee"], "related_entities": []}, {"description": "action postponed indefinitely", "date": "2025-06-03", "organization_id": "~{\"classification\": \"legislature\"}", "classification": [], "related_entities": []}], "sponsorships": [{"name": "Lanier, Steve D.", "classification": "primary", "entity_type": "person", "primary": true, "person_id": "~{\"name\": \"Lanier, Steve D.\"}", "organization_id": null}, {"name": "Tobiassen, Nicole", "classification": "primary", "entity_type": "person", "primary": true, "person_id": "~{\"name\": \"Tobiassen, Nicole\"}", "organization_id": null}, {"name": "Townsend, James G.", "classification": "primary", "entity_type": "person", "primary": true, "person_id": "~{\"name\": \"Townsend, James G.\"}", "organization_id": null}, {"name": "Woods, Pat", "classification": "primary", "entity_type": "person", "primary": true, "person_id": "~{\"name\": \"Woods, Pat\"}", "organization_id": null}], "related_bills": [], "versions": [{"note": "introduced version", "links": [{"url": "http://www.nmlegis.gov/Sessions/25%20Regular/bills/senate/SB0434.HTML", "media_type": "text/html"}, {"url": "http://www.nmlegis.gov/Sessions/25%20Regular/bills/senate/SB0434.PDF", "media_type": "application/pdf"}], "date": "", "classification": ""}, {"note": "ED substitute", "links": [{"url": "http://www.nmlegis.gov/Sessions/25%20Regular/bills/senate/SB0434EDS.HTML", "media_type": "text/html"}, {"url": "http://www.nmlegis.gov/Sessions/25%20Regular/bills/senate/SB0434EDS.PDF", "media_type": "application/pdf"}], "date": "", "classification": ""}, {"note": "Amendments in Context", "links": [{"url": "http://www.nmlegis.gov/Sessions/25%20Regular/Amendments_In_Context/SB0434.pdf", "media_type": "application/pdf"}], "date": "", "classification": ""}], "documents": [{"note": "ED committee report", "links": [{"url": "http://www.nmlegis.gov/Sessions/25%20Regular/bills/senate/SB0434ED1.HTML", "media_type": "text/html"}, {"url": "http://www.nmlegis.gov/Sessions/25%20Regular/bills/senate/SB0434ED1.PDF", "media_type": "application/pdf"}], "date": "", "classification": ""}, {"note": "FC committee report", "links": [{"url": "http://www.nmlegis.gov/Sessions/25%20Regular/bills/senate/SB0434FC1.HTML", "media_type": "text/html"}, {"url": "http://www.nmlegis.gov/Sessions/25%20Regular/bills/senate/SB0434FC1.PDF", "media_type": "application/pdf"}], "date": "", "classification": ""}, {"note": "Senate Floor Amendment 1", "links": [{"url": "http://www.nmlegis.gov/Sessions/25%20Regular/bills/senate/SB0434FS1.HTML", "media_type": ""}, {"url": "http://www.nmlegis.gov/Sessions/25%20Regular/bills/senate/SB0434FS1.PDF", "media_type": ""}], "date": "", "classification": ""}, {"note": "Fiscal Impact Report", "links": [{"url": "http://www.nmlegis.gov/Sessions/25%20Regular/firs/SB0434.PDF", "media_type": "application/pdf"}], "date": "", "classification": ""}, {"note": "LESC Analysis", "links": [{"url": "http://www.nmlegis.gov/Sessions/25%20Regular/LESCAnalysis/SB0434.PDF", "media_type": "application/pdf"}], "date": "", "classification": ""}], "citations": [], "sources": [{"url": "http://www.nmlegis.gov/Legislation/Legislation?chamber=S&legType=B&legNo=434&year=25", "note": ""}], "extras": {}, "jurisdiction": {"id": "ocd-jurisdiction/country:us/state:nm/government", "name": "New Mexico", "classification": "state", "division_id": "ocd-division/country:us/state:nm"}, "scraped_at": "2025-07-28T19:00:58+00:00", "_id": "31926f02-6be5-11f0-9367-8eb15cd3801a"}