{"legislative_session": "2025", "identifier": "HB107", "title": "PENALTY FOR DRUG TRAFFICKING & DEATH", "from_organization": "~{\"classification\": \"lower\"}", "classification": ["bill"], "subject": ["ALCOHOL & DRUGS", "CRIMES & PENALTIES"], "abstracts": [], "other_titles": [], "other_identifiers": [], "actions": [{"description": "Sent to House Pre-file", "date": "2025-01-15", "organization_id": "~{\"classification\": \"lower\"}", "classification": ["introduction", "referral-committee"], "related_entities": []}, {"description": "Sent to House Consumer & Public Affairs Committee & House Judiciary Committee", "date": "2025-01-27", "organization_id": "~{\"classification\": \"lower\"}", "classification": ["introduction", "referral-committee"], "related_entities": []}, {"description": "action postponed indefinitely", "date": "2025-06-03", "organization_id": "~{\"classification\": \"legislature\"}", "classification": [], "related_entities": []}], "sponsorships": [{"name": "Reeb, Andrea", "classification": "primary", "entity_type": "person", "primary": true, "person_id": "~{\"name\": \"Reeb, Andrea\"}", "organization_id": null}, {"name": "Chavez, Nicole", "classification": "primary", "entity_type": "person", "primary": true, "person_id": "~{\"name\": \"Chavez, Nicole\"}", "organization_id": null}, {"name": "Terrazas, Luis M.", "classification": "primary", "entity_type": "person", "primary": true, "person_id": "~{\"name\": \"Terrazas, Luis M.\"}", "organization_id": null}, {"name": "Ramos, Gabriel", "classification": "primary", "entity_type": "person", "primary": true, "person_id": "~{\"name\": \"Ramos, Gabriel\"}", "organization_id": null}, {"name": "Sena Cortez, Elaine", "classification": "primary", "entity_type": "person", "primary": true, "person_id": "~{\"name\": \"Sena Cortez, Elaine\"}", "organization_id": null}], "related_bills": [], "versions": [{"note": "introduced version", "links": [{"url": "http://www.nmlegis.gov/Sessions/25%20Regular/bills/house/HB0107.HTML", "media_type": "text/html"}, {"url": "http://www.nmlegis.gov/Sessions/25%20Regular/bills/house/HB0107.PDF", "media_type": "application/pdf"}], "date": "", "classification": ""}], "documents": [{"note": "Fiscal Impact Report", "links": [{"url": "http://www.nmlegis.gov/Sessions/25%20Regular/firs/HB0107.PDF", "media_type": "application/pdf"}], "date": "", "classification": ""}], "citations": [], "sources": [{"url": "http://www.nmlegis.gov/Legislation/Legislation?chamber=H&legType=B&legNo=107&year=25", "note": ""}], "extras": {}, "jurisdiction": {"id": "ocd-jurisdiction/country:us/state:nm/government", "name": "New Mexico", "classification": "state", "division_id": "ocd-division/country:us/state:nm"}, "scraped_at": "2025-07-28T18:17:25+00:00", "_id": "1c3fe1b2-6bdf-11f0-96d7-3e1447614032"}